pyclowder/__init__.py
pyclowder/client.py
pyclowder/collections.py
pyclowder/connectors.py
pyclowder/datasets.py
pyclowder/extractors.py
pyclowder/files.py
pyclowder/geostreams.py
pyclowder/sections.py
pyclowder/utils.py
pyclowder/api/__init__.py
pyclowder/api/v1/__init__.py
pyclowder/api/v1/datasets.py
pyclowder/api/v1/files.py
pyclowder/api/v2/__init__.py
pyclowder/api/v2/datasets.py
pyclowder/api/v2/files.py
pyclowder-3.0.8.dist-info/LICENSE
pyclowder-3.0.8.dist-info/METADATA
pyclowder-3.0.8.dist-info/WHEEL
pyclowder-3.0.8.dist-info/entry_points.txt
pyclowder-3.0.8.dist-info/top_level.txt
pyclowder-3.0.8.dist-info/RECORD
