Metadata-Version: 2.1
Name: pyclowder
Version: 3.0.8
Summary: Python SDK for the Clowder Data Management System
Home-page: https://clowderframework.org
Author: Rob Kooper
Author-email: kooper@illinois.edu
License: BSD
Project-URL: Bug Reports, https://github.com/clowder-framework/pyclowder/issues
Project-URL: Source, https://github.com/clowder-framework/pyclowder
Keywords: clowder,data management system
Classifier: Development Status :: 4 - Beta
Classifier: Intended Audience :: Science/Research
Classifier: License :: OSI Approved :: BSD License
Classifier: Programming Language :: Python :: 3
Classifier: Programming Language :: Python :: 3.6
Classifier: Programming Language :: Python :: 3.7
Classifier: Programming Language :: Python :: 3.8
Classifier: Programming Language :: Python :: 3.9
Classifier: Programming Language :: Python :: 3.10
Requires-Python: >=3.6, <4
License-File: LICENSE
Requires-Dist: pika
Requires-Dist: PyYAML
Requires-Dist: requests
Requires-Dist: requests-toolbelt
Provides-Extra: dev
Requires-Dist: check-manifest ; extra == 'dev'
Provides-Extra: test
Requires-Dist: coverage ; extra == 'test'
